sqsgenerator/_optimize.py
sqsgenerator/__init__.py
sqsgenerator/_adapters.py
sqsgenerator/__main__.py
sqsgenerator/core/_core.pyi
sqsgenerator/core/_core.cpython-314-darwin.so
sqsgenerator/core/__init__.py
sqsgenerator/cli/_version.py
sqsgenerator/cli/_cli.py
sqsgenerator/cli/__init__.py
sqsgenerator/cli/_shared.py
sqsgenerator/cli/_run.py
sqsgenerator/cli/_link.py
sqsgenerator/templates/__init__.py
sqsgenerator/templates/re-w.first.json
sqsgenerator/templates/ti-al-b-n.json
sqsgenerator-0.5.4.dist-info/RECORD
sqsgenerator-0.5.4.dist-info/WHEEL
sqsgenerator-0.5.4.dist-info/entry_points.txt
sqsgenerator-0.5.4.dist-info/METADATA
sqsgenerator-0.5.4.dist-info/licenses/LICENSE
